README.rst
setup.py
flask_navbar/__init__.py
flask_navbar/elements.py
flask_navbar/renderers.py
flask_navbar.egg-info/PKG-INFO
flask_navbar.egg-info/SOURCES.txt
flask_navbar.egg-info/dependency_links.txt
flask_navbar.egg-info/requires.txt
flask_navbar.egg-info/top_level.txt