Metadata-Version: 1.1
Name: flask-navbar
Version: 1.0
Summary: Easily create navigation for Flask applications. An extended copy of Flask_nav 0.6
Home-page: http://github.com/zcyuefan/flask-navbar
Author: zcyuefan
Author-email: zcyuefan@126.com
License: MIT
Platform: UNKNOWN
Classifier: Programming Language :: Python :: 2
Classifier: Programming Language :: Python :: 3
